bisc_package/__init__.py
bisc_package/cli.py
bisc_package/core/__init__.py
bisc_package/core/bisc_algorithm.py
bisc_package/core/mesh_pattern.py
bisc_package/core/permutation.py
bisc_package/examples/__init__.py
bisc_package/examples/bisc_demo.py
bisc_package/examples/known_classes/__init__.py
bisc_package/examples/known_classes/baxter_permutations.py
bisc_package/examples/known_classes/corrected_baxter_test.py
bisc_package/examples/known_classes/smooth_permutations.py
bisc_package/examples/known_classes/stack_sortable.py
bisc_package/examples/known_classes/test_baxter.py
bisc_package/examples/paper_examples/__init__.py
bisc_package/tests/__init__.py
bisc_package/tests/integration/__init__.py
bisc_package/tests/integration/bisc_simple_test.py
bisc_package/tests/integration/simple_verification.py
bisc_package/tests/integration/verify_examples.py
bisc_package/tests/unit/__init__.py
bisc_package/tests/unit/test_permutation.py
bisc_package/utils/__init__.py
bisc_package/utils/mesh_utils.py
bisc_package/utils/pattern_utils.py
bisc_algorithm-1.1.0.dist-info/LICENSE
bisc_algorithm-1.1.0.dist-info/METADATA
bisc_algorithm-1.1.0.dist-info/WHEEL
bisc_algorithm-1.1.0.dist-info/entry_points.txt
bisc_algorithm-1.1.0.dist-info/top_level.txt
bisc_algorithm-1.1.0.dist-info/RECORD
