Metadata-Version: 2.1
Name: bisc-algorithm
Version: 1.1.0
Summary: Implementation of the BiSC pattern discovery algorithm for permutations
Home-page: https://github.com/AcraeaTerpsicore/bisc-python
Author: BiSC Implementation Team
Author-email: BiSC Implementation Team <bisc-algorithm@example.com>
License: MIT License
Project-URL: Homepage, https://github.com/AcraeaTerpsicore/bisc-python
Project-URL: Documentation, https://bisc-python.readthedocs.io/
Project-URL: Repository, https://github.com/AcraeaTerpsicore/bisc-python
Project-URL: Bug Reports, https://github.com/AcraeaTerpsicore/bisc-python/issues
Project-URL: Paper, https://arxiv.org/abs/2411.17778
Keywords: permutations,patterns,combinatorics,algorithm,mathematics,pattern-discovery,mesh-patterns,automated-conjectures
Classifier: Development Status :: 4 - Beta
Classifier: Intended Audience :: Science/Research
Classifier: Intended Audience :: Education
Classifier: License :: OSI Approved :: MIT License
Classifier: Operating System :: OS Independent
Classifier: Programming Language :: Python :: 3
Classifier: Programming Language :: Python :: 3.7
Classifier: Programming Language :: Python :: 3.8
Classifier: Programming Language :: Python :: 3.9
Classifier: Programming Language :: Python :: 3.10
Classifier: Programming Language :: Python :: 3.11
Classifier: Topic :: Scientific/Engineering :: Mathematics
Classifier: Topic :: Software Development :: Libraries :: Python Modules
Classifier: Topic :: Education
Requires-Python: >=3.7
License-File: LICENSE
Provides-Extra: dev
Requires-Dist: pytest >=6.0 ; extra == 'dev'
Requires-Dist: pytest-cov >=2.10 ; extra == 'dev'
Requires-Dist: black >=22.0 ; extra == 'dev'
Requires-Dist: flake8 >=4.0 ; extra == 'dev'
Requires-Dist: mypy >=0.900 ; extra == 'dev'
Provides-Extra: docs
Requires-Dist: sphinx >=4.0 ; extra == 'docs'
Requires-Dist: sphinx-rtd-theme >=1.0 ; extra == 'docs'
Requires-Dist: sphinx-autodoc-typehints >=1.12 ; extra == 'docs'
Provides-Extra: jupyter
Requires-Dist: jupyter >=1.0 ; extra == 'jupyter'
Requires-Dist: matplotlib >=3.0 ; extra == 'jupyter'
Requires-Dist: numpy >=1.20 ; extra == 'jupyter'
